{"bookId":"whos-who-1940-pt7","title":"South African Indian Who's Who (1940)","totalPages":7,"indexedAt":"2026-03-31T21:01:15.641Z","pages":[{"page":1,"text":"344 THE SOUTH AFRICAN INDIAN WHO'S WHO Indian Cho “ Tell it to the Generation Following ” Was Who ABDOOLA Amod, former merchant; 6 Jodiya.dist. Jamnagar, Kathiwar) “came to South” Africa in the early dys Traded in Northern Natal and Transvaal ; opened own business as. gen ler at Amster ansvaal. Died at Durban. Survived by widow and severa sons and daughters who are. resident at Piet Retief, Transvaal AYOB, Noor Ma- homed ; }, Ranavav, Kathiwar, India, 1865! six s., three d.) educ Ranavav. Came to South Africa in 1887, landing at Durban, and, after short stay in Natal, went to Basutoland, eventually settled in Pretoria, where he started own business as merchant Later on opened branch in Johannes burg; was conducting large’ wholesale busi- ness with herd office at Pretoria at the time of his death ; was also a large pronerty owner, Left an estate of £120,000. Public activities ; Was first Indian to acquire immovable property in the name of a company in the Transvaal forming the first company known as The Land Trading Co., Ltd. Was a former secty. and a hfe trustee of the Pretoria Mohammedan Congregation v-presdt,, Transvaal Memon. Assocn. ; _ life-trustee Pretoria Memon Asvocn. Fducational Trust. Had been a generous donor to all deserving funds, including the Governor-General’s Fund, Turkish Mosque Fu and educational and public funds. Had earmarked a sum of £4,500 for an Indian school in Pretori Died Pretoria, Aug. 7, 1939, BAYAT, Amod ; cha,” about 1859 died at, Pletermarite, burg. 1931. On leaving India went to Mauri- tius where he resided for about ten years, Proceeding to Natal, here was’ in private employment, then started) own business in Mariteburg; was con- nected with it prac tically until the time of his death, Public activities : Was a keen public worker from the very early days. ‘Took a prominent. port the life of the community ndavion of the N.LC, : a member of the deputation to En} in 1909, to protest against the then licensing law of 1896 was a member of the South African Indian deputation to India in connection with the Class Areas Bill founder of Surat Suni Mosque and Madressa. P.M. Burg. urat, India, Durban, First 1886. Proceeded to the ‘Trans after a short stay, returned to Natal entering business wit his cousin, Dawood Ma- homed Bayat, at Dun- dee, 1890. ‘Transferred interests to Maritzburg, opened branch in Durban, 1917. Public work; Presit and a trustee of the Mohamedan Mosque and Madressa, Maritzburg, up to the time of his death: one of the founders of the Mohamedan Oriental School, for which he collected funds, adding a hostel and was responsible for bringing out teachers from India, 1918 | sccty Madressa Anjuman Islam, and West St. Mohamedan Mosque, Durban, up to the time of his death ; secty., Mota Varachha’ ‘Trust. Fund, Natal Branch; was chairman, Natal Indian Merchants’ Assocn. Is survived by awidow, four sons (Abdul Kader, Dawood, Cassim and Mahomed) and three daughters THE SOUTH AFRICAN I VDIAN WHO'S WHO 345 BHABHA, Amod Came to South Africa in 1888, ing one of the pioneer Indian merchants Settled in Middleburg, where he conducted” general dealer's business for 35 years. Was one of the leading Indians in district, being respected by all ‘sections of the community. On his death, the Middleburg Observer wrote: “It Mr. f it a fault—it was his extreme generosity. He was highly respected by all the old! Middleburgers who knew him. No call for charity or for the promotion of the town was ever turned down by the late A. E. Bhabha.” He was one of advanced outlook and devoted all his spare time to the study of English literature, politics, economics and religious subjects. He communicated his interest in these subjects to his children. While a devoted Muslim, he was a good Indian and his acts ‘of generosity and benevolerice touched all sections ‘of the community. He took part in the passive resistance movement under Mr. Gandhi, serving a term of imprisonment. The water supply of Mr. Bhabha’s native town, Kholvad, in the Surat district, is derived from the ground given in charity by him: BILLIMORIA, Am- baram Latloo; also known as Motiram Morar; \"6. Bilimora, 197 ; ‘educ. Bilimora } came’ to South Africa, 1910; settled in Nigel, Transvaal ; then went to Springs, being at periods, in. Beno Roksburg, Germiston, Johannesburg, Koode poort and Krugersdorp. Started business as merchant tailor in 1915 ; prior to this was in father's business. Public work : Presitt of Transvaal Dargi Mundal ; secty., Hindu Dharma Sabha Krugersdorp : former secty., Krugersdorp Indian Community. Had been connected with public Me since carly days, a boy when associated with Mahatma Gandhi at the Tolstoy farm; repsd. Transvaal at C, Conferences, Kimberley, 1928 and Cape Town, ‘Always took leading part in all public affairs both in South Africa and in India, Died in India, 1937 BOBAT, Hajee Is- mail Mahomed ; was Commissioner ‘0: Oaths, Durban}. Kathor, India, 1880; edue Kathor. In 1802 came to South Africa and joined the firm of nele, Hajce Da wood Mahomed. — In 1903 one of the founders and partners in the firm of B Ebrahim, Ismail & Co., wholesale merchants at one time the leading Indian business. firm in Natal. Also director and chairman of the Kathorian Trading Co. (Dty.), Ltd. Was principal Indian representative of the London and Lancashire Insurance Co. Public work: “Was chairman, Indian Chamber of Commerce, one of those responsible for compiling vatuable information contained in The Indian, Vrader, a statement submitted to the Sir Farli Hussain’ Delegation, Was acti all affairs of the Indian community, und hada pro Rressive outlook. Highly respected by all. sections of the community. Was presdt., Orient Club, Isipingo In India founded the Mebfile Ronakal. Islam—-the Charitable Zanana Diypensary—at Ki Made Pilgrimage to Mecca, 1986. ‘Died . Reb. 9: survived by widow, one s., two BODASING, Bas- daw Singh; 'b. Xe Sueldecland, 1893 ds. of Inte Babu Bodasing; twos three d. ; “edue. Higher Grade ‘Government Indian School, Duy Was one of the Ic Indian cane pla mn Natal. Once p cricket and soccer V.spresdt., North Coast Indian Football Assocn. ; presented, tly with brothers » KR, and N., the Bodasing Memorial Cup, the premier soccer trophy for the North Coast. _V.-presdt, Stanger Hindi School. Was treas., New Guelderland Mil Group ; was presdt,, Arya Prithnidi Sabha; donor Currie's Fountain Ground Clock, Visited India, 1932-33, met many eminent Indians, Died 1939.","records":[{"fullName":"344 THE","rawText":"344 THE SOUTH AFRICAN INDIAN WHO'S WHO Indian Cho “ Tell it to the Generation Following ” Was Who ABDOOLA Amod, former merchant; 6 Jodiya.dist. Jamnagar, Kathiwar) “came to South” Africa in the early dys Traded in Northern Natal and Transvaal ; opened own business as. gen ler at Amster ansvaal. Died at Durban. Survived by widow and severa sons and daughters who are. resident at Piet Retief, Transvaal AYOB, Noor Ma- homed ; }, Ranavav, Kathiwar, India, 1865! six s., three d.) educ Ranavav. Came to South Africa in 1887, landing at Durban, and, after short stay in Natal, went to Basutoland, eventually settled in Pretoria, where he started own business as merchant Later on opened branch in Johannes burg; was conducting large’ wholesale busi- ness with herd office at Pretoria at the time of his death ; was also a large pronerty owner, Left an estate of £120,000. Public activities ; Was first Indian to acquire immovable property in the name of a company in the Transvaal forming the first company known as The Land Trading Co., Ltd. Was a former secty. and a hfe trustee of the Pretoria Mohammedan Congregation v-presdt,, Transvaal Memon. Assocn. ; _ life-trustee Pretoria Memon Asvocn. Fducational Trust. Had been a generous donor to all deserving funds, including the Governor-General’s Fund, Turkish Mosque Fu and educational and public funds. Had earmarked a sum of £4,500 for an Indian school in Pretori Died Pretoria, Aug. 7, 1939, BAYAT, Amod ; cha,” about 1859 died at, Pletermarite, burg. 1931. On leaving India went to Mauri- tius where he resided for about ten years, Proceeding to Natal, here was’ in private employment, then started) own business in Mariteburg; was con- nected with it prac tically until the time of his death, Public activities : Was a keen public worker from the very early days. ‘Took a prominent. port the life of the community ndavion of the N.LC, : a member of the deputation to En} in 1909, to protest against the then licensing law of 1896 was a member of the South African Indian deputation to India in connection with the Class Areas Bill founder of Surat Suni Mosque and Madressa. P.M. Burg. urat, India, Durban, First 1886. Proceeded to the ‘Trans after a short stay, returned to Natal entering business wit his cousin, Dawood Ma- homed Bayat, at Dun- dee, 1890. ‘Transferred interests to Maritzburg, opened branch in Durban, 1917. Public work; Presit and a trustee of the Mohamedan Mosque and Madressa, Maritzburg, up to the time of his death: one of the founders of the Mohamedan Oriental School, for which he collected funds, adding a hostel and was responsible for bringing out teachers from India, 1918 | sccty Madressa Anjuman Islam, and West St. Mohamedan Mosque, Durban, up to the time of his death ; secty., Mota Varachha’ ‘Trust. Fund, Natal Branch; was chairman, Natal Indian Merchants’ Assocn. Is survived by awidow, four sons (Abdul Kader, Dawood, Cassim and Mahomed) and three daughters THE SOUTH AFRICAN I VDIAN WHO'S WHO 345 BHABHA, Amod Came to South Africa in 1888, ing one of the pioneer Indian merchants Settled in Middleburg, where he conducted” general dealer's business for 35 years. Was one of the leading Indians in district, being respected by all ‘sections of the community. On his death, the Middleburg Observer wrote: “It Mr. f it a fault—it was his extreme generosity. He was highly respected by all the old! Middleburgers who knew him. No call for charity or for the promotion of the town was ever turned down by the late A. E. Bhabha.” He was one of advanced outlook and devoted all his spare time to the study of English literature, politics, economics and religious subjects. He communicated his interest in these subjects to his children. While a devoted Muslim, he was a good Indian and his acts ‘of generosity and benevolerice touched all sections ‘of the community. He took part in the passive resistance movement under Mr. Gandhi, serving a term of imprisonment. The water supply of Mr. Bhabha’s native town, Kholvad, in the Surat district, is derived from the ground given in charity by him: BILLIMORIA, Am- baram Latloo; also known as Motiram Morar; \"6. Bilimora, 197 ; ‘educ. Bilimora } came’ to South Africa, 1910; settled in Nigel, Transvaal ; then went to Springs, being at periods, in. Beno Roksburg, Germiston, Johannesburg, Koode poort and Krugersdorp. Started business as merchant tailor in 1915 ; prior to this was in father's business. Public work : Presitt of Transvaal Dargi Mundal ; secty., Hindu Dharma Sabha Krugersdorp : former secty., Krugersdorp Indian Community. Had been connected with public Me since carly days, a boy when associated with Mahatma Gandhi at the Tolstoy farm; repsd. Transvaal at C, Conferences, Kimberley, 1928 and Cape Town, ‘Always took leading part in all public affairs both in South Africa and in India, Died in India, 1937 BOBAT, Hajee Is- mail Mahomed ; was Commissioner ‘0: Oaths, Durban}. Kathor, India, 1880; edue Kathor. In 1802 came to South Africa and joined the firm of nele, Hajce Da wood Mahomed. — In 1903 one of the founders and partners in the firm of B Ebrahim, Ismail & Co., wholesale merchants at one time the leading Indian business. firm in Natal. Also director and chairman of the Kathorian Trading Co. (Dty.), Ltd. Was principal Indian representative of the London and Lancashire Insurance Co. Public work: “Was chairman, Indian Chamber of Commerce, one of those responsible for compiling vatuable information contained in The Indian, Vrader, a statement submitted to the Sir Farli Hussain’ Delegation, Was acti all affairs of the Indian community, und hada pro Rressive outlook. Highly respected by all. sections of the community. Was presdt., Orient Club, Isipingo In India founded the Mebfile Ronakal. Islam—-the Charitable Zanana Diypensary—at Ki Made Pilgrimage to Mecca, 1986. ‘Died . Reb. 9: survived by widow, one s., two BODASING, Bas- daw Singh; 'b. Xe Sueldecland, 1893 ds. of Inte Babu Bodasing; twos three d. ; “edue. Higher Grade ‘Government Indian School, Duy Was one of the Ic Indian cane pla mn Natal. Once p cricket and soccer V.spresdt., North Coast Indian Football Assocn. ; presented, tly with brothers » KR, and N., the Bodasing Memorial Cup, the premier soccer trophy for the North Coast. _V.-presdt, Stanger Hindi School. Was treas., New Guelderland Mil Group ; was presdt,, Arya Prithnidi Sabha; donor Currie's Fountain Ground Clock, Visited India, 1932-33, met many eminent Indians, Died 1939."}]},{"page":2,"text":"THE BRAMDAW, Dabee, retired civil ‘servant | five s., three di: 6. ' Pietermaritzburg, Nov 5, 1881; educ, One of the few Indians of the Province who had the benefit of being ed- ucated at a European school, namely, the Boys’ Model School P.M.B. Private study thereafter, Passed Inion lower Law Exam. Managing clerk in legal ‘offices, Ad- mitted Sworn 1 lator of the Supreme Court of S.A. Joined Civil Service July 13, 1913, and served in Courts of Magistrates for districts of Umlazi, Verulam, Bulwer, Stanger and Pinetown, Acted as Clerk to Returning Officer for Provincial Council and Legislative Assembly elections, as Clerk of Court, and served as Clerk to Rural Licensing Board. ‘Specially appointed by Govt. to give evidence before the Graham Commission (Public Service’. Author of the official report to Govt. on the Indian strike at Verulam and district 1913. Invited to draft Rural Licensing Board regula tions. Except for sitting on the Bench has performed all work within the jurisdiction of a Magistrate's court in the administration of justice and public affairs. Public service; Led severe! deputations to Education Dept., and instrumental in establishing several Govt. schools at Stanger and Pinetown: with others, established first Arya Samaj in South Africa In Sport : Introduced Five-a-side competition among Indians in Natal; Life v.epresdt.. M-DALE-A. Kirst India pavs referee's exatnination, conducted by eof the MD.FA. (European). Died Durban, 1935, CHOONOO, John; 6. in G and when quite young went to Mauritius, where for several years served as a_catechist_ under the Church Missionary Society. He married in Mauritius and there his wife him, leav He married left for Natal in Seo ember, i880, In 1882 he began his mission: ary career under the Weslevan Methodist Church of South Africa which he served for years without a break. His activities extended on the coast telt of Natal, where he helped to build a number of churches and’ Indian shoots. Two of his sons, Reuben and Arthur, are Methodist ministers, and ‘three others, Timothy, Ezekiel and Walter, are head teachers of Government-Aided schools’ at SOUTH AFRICAN INDIAN Ton at th 19 WHO'S nginat His. wife CACHALIA, Ahmed Mahomed of the chatrman Transvaal British Indian Assocn ms. He Periods of of the staunchest Resistance ment and allowed him: to be made insol vent rather than violate lus oath, serjuently paying hi Credntors im fall, DAHYA Naran ; Navasari Presidency, ¢ educ. Navasati. ¢. s. of Bombay Iss late Naran Moolchand Came out to Natal as a youngster, stayed in various parts of Natal. gaining experience in trade of this country Returned to India coming ont again ia 1913, wiven established successful business at Mayville, Public ac- tivities | Was. inter- ested in all activities of the community Memier, Surat Hindu Assocn. and 120 Natal Main Road. Mayville, WHO Prospect-Hail Indian Congress 1936. Survived by widow, three s., four DAWOOD, homed, lea Ma merchant and ler, One of the out- standing leaders of the Indian Died in Natal DEWAN, Rad community. Hydzrahad Sind, ban. Died, respectivel hr age of 93 years on Easter Su thed 8 monthy later on Traded at a Cet. 6, April 18, 1939, THE SOUTH DALA, Mahomed [>> Ismail ; &. P. Tatnow Burma, 1874; _ educ Kathor. In 1887 went auritius, where en- gaged first’ in store ig. In 1890 came tal, settling in Dundee. ' After two years’ private employ ment,opened own bust- ness as general dealer in Dundee, Natal. In I left for Cape Since then had engaged in busi- hess as general dealer (draper, “grocer, *tc.), til his death. Keenly interested in education ; son had qualified in medicine from Liverpool and London Universities Another three daughters and one son are engaged in his former business at 21-27, Hanover Street, Capetown. Visited England and Continent in L028. Died at Capetown, 1938 EBRAHIM, Ma- homed (of the firm of M. Ebrahim Soondka. Ltd); Ranavav 1882\" edu. Ranavav Came to South Africa in 1912, setthng in Pretoria. First was partner in brother's business in name of XN. M. Ebrahim, but resigned in order to start own business wholesale nel direct A quiet worker in the causeof the community. Died 1 Indra, 1934 GANESS, Aympa- rumul Moodley ; 6. Rosehill, Mauritius, 1887 ; ede. Mauritins ys. of late Ayna Moodtey. Came\" to South Africa in 1901, settled in Port Eliza beth, where started business as fish desler. which he had developed scale Owned a fleet of four motor boats for fishing. led in own name of A. Ganess, wholesale and retail ‘fish mer- chants. Public actres- tues; Was member of the Cape Indian Congress (Port Elizabeth Branch) : member of the Siva Soobramanium Hindu Temple committee member of the Saraswati Educational Institute, Port Elizabeth. Died at Port Flizabeth, 1938 AFRICA? INDIAN WHO'S WHO 347 GANI, Abdool Reh- man, 'Abdool ; Vadashda, Kathiwar, 1885 ; edi four s., twe South’ Africa in 1898, stayed first at Potch- efstroom, with grand father — Hajee Mahomed_and joined in father's business trading as A.G.H.S. Mahomed and Sons. When father returned to India in 1914 re. tiring from business, took over entire con trol, changing firm name to. R.A. Gani Returned to India, 1925, coming back 1927. In 1930 removed to Klerksdorp and opened biggest Indian firm there, carrying on in firm name of Gani’s Bombay House. This business had branches in India—tsmail Abdoo! Kehman and Co., Mopla Buildings, first floor, Abdool Rehman St.. Rombav : at Vizianagram, India trading as Ismail Abdool Kehman and Co.. and at Seetakol in sai a branch exists at Chhindwara, as Amod Haice fatib and C Public actioitics: Was Chairman, British Indian Assocn.. Potchefstroom, 1918-193; repsd. Transvaal at Sessions of S.A.LC.; wax responsible for inviting Mr. Sastri for laying foundation stone Indian School. Potchefstrooni entertained members Sir Fazli tion, on its stay in Klerksdorp, en route invited the representatives of the Govern= was responsible for for India ment of India in South rica visit of Kunwar Sie Maharaj Singh in 1933; was member of Ti IIndian Congress deputation to Cape Town in 1934, Was an actiwe participant in all public affairs affecting the indian, community was chairman Kutivana Kathiwan Ektul der Dhorma Sala in Kutiyana, Kathiwar. Was Keen on sport. extending his help so that it ht be means of developing the physique of young Indians. Was highly respected by all Europeans, olticials and members of the public. Died at Klerks- dorp, June 21, 1938 GIDOOMAL, Daya- ram 5b. Hyderabad Sind,” 1892 duc Hyderabad. Sind Came to South Africa in 1907, settled in Johannesburg. Here I the firm of his le. D. P. Gidoomal, sille merchants. In 8 with. partners started the Japan Bazaar, which had been developed into one of the leading Indian es- tablishments in the city of Johannesburg. Died during his visit to Capetown, Oct. 23, 1936.","records":[{"fullName":"THE BRAMDAW,","rawText":"THE BRAMDAW, Dabee, retired civil ‘servant | five s., three di: 6. ' Pietermaritzburg, Nov 5, 1881; educ, One of the few Indians of the Province who had the benefit of being ed- ucated at a European school, namely, the Boys’ Model School P.M.B. Private study thereafter, Passed Inion lower Law Exam. Managing clerk in legal ‘offices, Ad- mitted Sworn 1 lator of the Supreme Court of S.A. Joined Civil Service July 13, 1913, and served in Courts of Magistrates for districts of Umlazi, Verulam, Bulwer, Stanger and Pinetown, Acted as Clerk to Returning Officer for Provincial Council and Legislative Assembly elections, as Clerk of Court, and served as Clerk to Rural Licensing Board. ‘Specially appointed by Govt. to give evidence before the Graham Commission (Public Service’. Author of the official report to Govt. on the Indian strike at Verulam and district 1913. Invited to draft Rural Licensing Board regula tions. Except for sitting on the Bench has performed all work within the jurisdiction of a Magistrate's court in the administration of justice and public affairs. Public service; Led severe! deputations to Education Dept., and instrumental in establishing several Govt. schools at Stanger and Pinetown: with others, established first Arya Samaj in South Africa In Sport : Introduced Five-a-side competition among Indians in Natal; Life v.epresdt.. M-DALE-A. Kirst India pavs referee's exatnination, conducted by eof the MD.FA. (European). Died Durban, 1935, CHOONOO, John; 6. in G and when quite young went to Mauritius, where for several years served as a_catechist_ under the Church Missionary Society. He married in Mauritius and there his wife him, leav He married left for Natal in Seo ember, i880, In 1882 he began his mission: ary career under the Weslevan Methodist Church of South Africa which he served for years without a break. His activities extended on the coast telt of Natal, where he helped to build a number of churches and’ Indian shoots. Two of his sons, Reuben and Arthur, are Methodist ministers, and ‘three others, Timothy, Ezekiel and Walter, are head teachers of Government-Aided schools’ at SOUTH AFRICAN INDIAN Ton at th 19 WHO'S nginat His. wife CACHALIA, Ahmed Mahomed of the chatrman Transvaal British Indian Assocn ms. He Periods of of the staunchest Resistance ment and allowed him: to be made insol vent rather than violate lus oath, serjuently paying hi Credntors im fall, DAHYA Naran ; Navasari Presidency, ¢ educ. Navasati. ¢. s. of Bombay Iss late Naran Moolchand Came out to Natal as a youngster, stayed in various parts of Natal. gaining experience in trade of this country Returned to India coming ont again ia 1913, wiven established successful business at Mayville, Public ac- tivities | Was. inter- ested in all activities of the community Memier, Surat Hindu Assocn. and 120 Natal Main Road. Mayville, WHO Prospect-Hail Indian Congress 1936. Survived by widow, three s., four DAWOOD, homed, lea Ma merchant and ler, One of the out- standing leaders of the Indian Died in Natal DEWAN, Rad community. Hydzrahad Sind, ban. Died, respectivel hr age of 93 years on Easter Su thed 8 monthy later on Traded at a Cet. 6, April 18, 1939, THE SOUTH DALA, Mahomed [>> Ismail ; &. P. Tatnow Burma, 1874; _ educ Kathor. In 1887 went auritius, where en- gaged first’ in store ig. In 1890 came tal, settling in Dundee. ' After two years’ private employ ment,opened own bust- ness as general dealer in Dundee, Natal. In I left for Cape Since then had engaged in busi- hess as general dealer (draper, “grocer, *tc.), til his death. Keenly interested in education ; son had qualified in medicine from Liverpool and London Universities Another three daughters and one son are engaged in his former business at 21-27, Hanover Street, Capetown. Visited England and Continent in L028. Died at Capetown, 1938 EBRAHIM, Ma- homed (of the firm of M. Ebrahim Soondka. Ltd); Ranavav 1882\" edu. Ranavav Came to South Africa in 1912, setthng in Pretoria. First was partner in brother's business in name of XN. M. Ebrahim, but resigned in order to start own business wholesale nel direct A quiet worker in the causeof the community. Died 1 Indra, 1934 GANESS, Aympa- rumul Moodley ; 6. Rosehill, Mauritius, 1887 ; ede. Mauritins ys. of late Ayna Moodtey. Came\" to South Africa in 1901, settled in Port Eliza beth, where started business as fish desler. which he had developed scale Owned a fleet of four motor boats for fishing. led in own name of A. Ganess, wholesale and retail ‘fish mer- chants. Public actres- tues; Was member of the Cape Indian Congress (Port Elizabeth Branch) : member of the Siva Soobramanium Hindu Temple committee member of the Saraswati Educational Institute, Port Elizabeth. Died at Port Flizabeth, 1938 AFRICA? INDIAN WHO'S WHO 347 GANI, Abdool Reh- man, 'Abdool ; Vadashda, Kathiwar, 1885 ; edi four s., twe South’ Africa in 1898, stayed first at Potch- efstroom, with grand father — Hajee Mahomed_and joined in father's business trading as A.G.H.S. Mahomed and Sons. When father returned to India in 1914 re. tiring from business, took over entire con trol, changing firm name to. R.A. Gani Returned to India, 1925, coming back 1927. In 1930 removed to Klerksdorp and opened biggest Indian firm there, carrying on in firm name of Gani’s Bombay House. This business had branches in India—tsmail Abdoo! Kehman and Co., Mopla Buildings, first floor, Abdool Rehman St.. Rombav : at Vizianagram, India trading as Ismail Abdool Kehman and Co.. and at Seetakol in sai a branch exists at Chhindwara, as Amod Haice fatib and C Public actioitics: Was Chairman, British Indian Assocn.. Potchefstroom, 1918-193; repsd. Transvaal at Sessions of S.A.LC.; wax responsible for inviting Mr. Sastri for laying foundation stone Indian School. Potchefstrooni entertained members Sir Fazli tion, on its stay in Klerksdorp, en route invited the representatives of the Govern= was responsible for for India ment of India in South rica visit of Kunwar Sie Maharaj Singh in 1933; was member of Ti IIndian Congress deputation to Cape Town in 1934, Was an actiwe participant in all public affairs affecting the indian, community was chairman Kutivana Kathiwan Ektul der Dhorma Sala in Kutiyana, Kathiwar. Was Keen on sport. extending his help so that it ht be means of developing the physique of young Indians. Was highly respected by all Europeans, olticials and members of the public. Died at Klerks- dorp, June 21, 1938 GIDOOMAL, Daya- ram 5b. Hyderabad Sind,” 1892 duc Hyderabad. Sind Came to South Africa in 1907, settled in Johannesburg. Here I the firm of his le. D. P. Gidoomal, sille merchants. In 8 with. partners started the Japan Bazaar, which had been developed into one of the leading Indian es- tablishments in the city of Johannesburg. Died during his visit to Capetown, Oct. 23, 1936.","profession":"THE BRAMDAW, Dabee, retired civil ‘servant | five s"}]},{"page":3,"text":"348, TH GOOLAM, Rasool ; (known alsd as Moon: shi): Commissioner for Oaths; 6. Lady- smith, Natal,” 1887 edwc. ‘Natal. ‘In 1908 started own business ay financial, commer. cial and general agent. secty. for companies agent for the } orkshire Insurance Co., Ltd. at Pietersburg. \"Had an extensive practice as bookkeeper in the Nortbern Transvaal Official. interpreter of the Mayistrate's Court at Pietersburg. — Ap pointed Commissioner of Oaths for Pietersburg and District in 1935. Public actiuties ; Was the secty of Northern Transvaal Indian Assocn, and secty. of the Mohammedan Congreyation of Pietersburg. He wax well known throughout the Union, contested several actions for the benefit of the Indian community, namely, Immigration cases, Transvaal Licence Control Ordinance, Post Office case. Died as a result of a motor accident. September, 1930, JOSHUA, Joseph Samuel, Commissioner of Oathi 6, Bere fan, Feb, 22, 1872 im, Mary Charlotte, 3rd d, of late S. Godfrey ; educ. Boys’ Model School, Durban, Just after ‘leaving ‘school won the Gandhi Prize awarded for the best essay on “India, and what it can teach us. Entered service ot the tal Government Railway as messenger, promoted clerk and clerk-in-charge of cor- respondence under (late) Sir David Hunter. On transfer to Department of Justice was presented with a parchment testimonial, being the only Indian to possess it. In 1901 was appointed clerk and interpreter at the Umgeni Court, Maritzburg. In 1912 transferred on promotion. to. Verulam, ‘where remained till retirement in 1932. On retirement was thanked by the Department of Justice for meritorious services and as a mark of Appreciation was made a Commissioner for Oaths, being the first Natal-born Indian to be thus honoured During his period of service was specially appointed to act as interpreter to a number of important com- missions, including the inquiry of Indian indentured labour at Umzinto, ete. During the visit of H.R.H. the Prince of Wales to Verulam, was one of the five Indians selected to be presented to him. In early SOUTH AFRICAD INDIAN WHO'S WHO days was a keen sportsman, being one of the foundati members of the Blue Bells FC. and ‘the F.C. and a founder of the Greyville ¢ presdt. of the Natal Indian Football Assocn.> presdt JASSAT, Ismail Amod; )._Kholvad. Baroda State, 187i: educ. Kholvad. In 1887 went to Mauritius, working in his brother's firm for several years. Re: turned to India and married. In 1895 came to South Africa, staying in Johannesburg, soon after started xeneral dealer’s business at Ermelo. During Boer War until war was over ng his absence. Returned in sin Standerton in firm name eneral dealers. In 1903 re- started business at Ermelo in name of Amod and Ismail. being in charge of the Ermelo branch. In 1917 partnership was dissolved, since then has carried on business by himself. retaining the firm name of Amod and Ismail, subsequently including his sons as partners, Goolam Hoosen Jassat, Mahomed Ismail’ Jassat and = Moosa Ismail Jassat daughters, ali children born in Ermelo, Public work > Was chairman and trustee. Ermelo mosque : one of founders Frmelo Government Indian School: chairman, Indian Government School Committee. Took active part in education, social and general affairs of the Indian community.\" Died Ermelo, Transvaal, 1938 JUGADOE, Dabee ; b. Pietermaritzburg only brother of Dabee Bramdaw ; edue Pietermaritzburz, connected with The Natal Witness Pub- lishing Department Public activities Former v.-presdt M.D.LF.A.; patron, and life v Schools’ F.C. y years; mem: Me PMB Branch) ; was secty., Veda Dhrama Sabha, P.AMLB.; was a mem: ber of the “Strike Committee” during the passive resistance movement of 1913; took a close interest in all public affair Died at ‘Pietermaritzburg, Feb. 11, 1937. KHARVA, Hajee Ismail Amod; died October, 1939. Biography on page 137 THE SOUTH AFRICAN KALIAN | Gopal merchant tailor Varad diet Surat 1880; | 3rd s. of late Gopai Vala, of Varad four <. (Gulab, Nagin Ratila! and Harila!) Came to South Africa in 1912, settled in Jo- hannesburg, where started own business as merchant tailor trading as V. Bhan: bhai & Co. (the bu ness is now bein: ducted by Gulab Kal- ian). Public activities Was chairman and also treas. for a long period up to the time of his death of the Transvaal Dargi Mundal: mentber of the managing committee of the Bespoke 3 Employers’ Assoca.; committee member of the Transvaal Hindw Siva’Samai: also contributed his share to public work. Died at Johannesburg, April 15, 1937. KHAN. Kazi Beblol: dist, Surat andvi Gujarati and. “Arabic, Children: 6 sons and 4 daughters. Came to South Africa in Oct. 1894, landed at Dur ban.” “After a short stay. proceeded to Jo hannesburg. From Jo- hannesburg went to Zeerust in 1898 and then to Bulawayo, 5. Rhodesia. being one of the pioneer Indians and among. the first to. secure” the fra chise; he also inter- ested himself in acquiring a cémetery for Muslims. With headquarters in Bulawayo he carried on business in various parts, ma ps to Bechuanaland and the Kalahari. From 1901-6. established _ business, with six branch stores at Zeerust. in the firm name of B. B. Khan & Co, In 1906 transferred interests to Lichtenburg, where the firm, with four branch stores, is still actively engaged in commerce. being one of the leading Indian businesses in the district Thereisa wholesale buying house at cr. Kort & Commis: sionerSt., Johannesburg. Publicactivities: In 1911an active member of the Home Rule League. a strong sup- porter of Hindu-Musli co-operation. Took a prominent part in the public life of Mandvi; in 1919 founded the Mandvi Public Library; in 1922-25 being connected with Mahatma Gandhr’s movement, while loyal to the British connection was still patriotic in serving the interests of his countrymen: was v-presdt., Mandvi High School; patron, Mandvi Educational Society ; was presdt., Mandvi Khalifat Committee. In South Africa took part in the Passive Resistance struggle, 1908-14 ; had taken interest in all public efforts, contributing both service an money. Died in Johannesburg, March 12, 1937 I DIAN WHO'S WHO 349 KHAN, Rahim Karim; was Barrister- at-law, member of Lin- coln’s Inn; member Supreme Court of Judi- cature and; ad- vocate Supreme Court of South Africa (X.P.D.): b, Bomba: March 24, 1874: di Oct. 8, 1932. Daring Boer War acted as leader of Ambulance Corps at Colenso and Spion Kop, ete... giving services free, for which he was thanked by Government and decorated with the usual medal; was for many years joint secty. of the Natal Indian Congress. Repstd. Natal at S,ALC Conferences: was appointed by Government of Natal as member of Board of Examiners for Indian languages, On his death left practically his whole estate, ex ceeding £40,000, for Indian medical relief MEER, Cassim Hajee Suleman; & Surat City, Oct. 12, 1884. Died at Dundee, May'30, Educ. Surat city. Came to South Africa in 1896, Settled in Dundee, where he was in bus ness. He leading 1 district, prominently identifying himselt with public work Chairman of the Natal Indian Congress, Dui dee Branch; presdt of the Northern Natal Chamber of Commerce: presdt. of the Muslim Congrega Dundee and District Indian Football Assocn. ; was an official of practically all public bodies in Northern Natal; was a member of Congress deputation to the Minister of the Interior, Dr. D. I, Malan, in connection with the Class Areas Bill, 1925; repstd Natal at the S.A.1.C. Conferences from 1919. Was also a large donor of the Sastri College Building Fund. one of those responsible for starting the India Was a strong advocate of 3 In India repstd. Surat City at the All-India, Muslim. Educational Conference,” etected as one of the members of the reception committee Of 17; joint secty. of the reception committee of the All-india National Congress held at Surat City ; was a large donor towards, and instrumental toa great extent in, the erection of the Surat Islam Yatimkhana; first chairman of its committee. Collected a I money for the Khalifat Fund, which was signally recognised by its committee. consisting of distinguished Muslims. He is survived by his widow and the soas are Yousuf, Ebrahim, Mahomed and Suleman. presdt. of the","records":[{"fullName":"348, TH","rawText":"348, TH GOOLAM, Rasool ; (known alsd as Moon: shi): Commissioner for Oaths; 6. Lady- smith, Natal,” 1887 edwc. ‘Natal. ‘In 1908 started own business ay financial, commer. cial and general agent. secty. for companies agent for the } orkshire Insurance Co., Ltd. at Pietersburg. \"Had an extensive practice as bookkeeper in the Nortbern Transvaal Official. interpreter of the Mayistrate's Court at Pietersburg. — Ap pointed Commissioner of Oaths for Pietersburg and District in 1935. Public actiuties ; Was the secty of Northern Transvaal Indian Assocn, and secty. of the Mohammedan Congreyation of Pietersburg. He wax well known throughout the Union, contested several actions for the benefit of the Indian community, namely, Immigration cases, Transvaal Licence Control Ordinance, Post Office case. Died as a result of a motor accident. September, 1930, JOSHUA, Joseph Samuel, Commissioner of Oathi 6, Bere fan, Feb, 22, 1872 im, Mary Charlotte, 3rd d, of late S. Godfrey ; educ. Boys’ Model School, Durban, Just after ‘leaving ‘school won the Gandhi Prize awarded for the best essay on “India, and what it can teach us. Entered service ot the tal Government Railway as messenger, promoted clerk and clerk-in-charge of cor- respondence under (late) Sir David Hunter. On transfer to Department of Justice was presented with a parchment testimonial, being the only Indian to possess it. In 1901 was appointed clerk and interpreter at the Umgeni Court, Maritzburg. In 1912 transferred on promotion. to. Verulam, ‘where remained till retirement in 1932. On retirement was thanked by the Department of Justice for meritorious services and as a mark of Appreciation was made a Commissioner for Oaths, being the first Natal-born Indian to be thus honoured During his period of service was specially appointed to act as interpreter to a number of important com- missions, including the inquiry of Indian indentured labour at Umzinto, ete. During the visit of H.R.H. the Prince of Wales to Verulam, was one of the five Indians selected to be presented to him. In early SOUTH AFRICAD INDIAN WHO'S WHO days was a keen sportsman, being one of the foundati members of the Blue Bells FC. and ‘the F.C. and a founder of the Greyville ¢ presdt. of the Natal Indian Football Assocn.> presdt JASSAT, Ismail Amod; )._Kholvad. Baroda State, 187i: educ. Kholvad. In 1887 went to Mauritius, working in his brother's firm for several years. Re: turned to India and married. In 1895 came to South Africa, staying in Johannesburg, soon after started xeneral dealer’s business at Ermelo. During Boer War until war was over ng his absence. Returned in sin Standerton in firm name eneral dealers. In 1903 re- started business at Ermelo in name of Amod and Ismail. being in charge of the Ermelo branch. In 1917 partnership was dissolved, since then has carried on business by himself. retaining the firm name of Amod and Ismail, subsequently including his sons as partners, Goolam Hoosen Jassat, Mahomed Ismail’ Jassat and = Moosa Ismail Jassat daughters, ali children born in Ermelo, Public work > Was chairman and trustee. Ermelo mosque : one of founders Frmelo Government Indian School: chairman, Indian Government School Committee. Took active part in education, social and general affairs of the Indian community.\" Died Ermelo, Transvaal, 1938 JUGADOE, Dabee ; b. Pietermaritzburg only brother of Dabee Bramdaw ; edue Pietermaritzburz, connected with The Natal Witness Pub- lishing Department Public activities Former v.-presdt M.D.LF.A.; patron, and life v Schools’ F.C. y years; mem: Me PMB Branch) ; was secty., Veda Dhrama Sabha, P.AMLB.; was a mem: ber of the “Strike Committee” during the passive resistance movement of 1913; took a close interest in all public affair Died at ‘Pietermaritzburg, Feb. 11, 1937. KHARVA, Hajee Ismail Amod; died October, 1939. Biography on page 137 THE SOUTH AFRICAN KALIAN | Gopal merchant tailor Varad diet Surat 1880; | 3rd s. of late Gopai Vala, of Varad four <. (Gulab, Nagin Ratila! and Harila!) Came to South Africa in 1912, settled in Jo- hannesburg, where started own business as merchant tailor trading as V. Bhan: bhai & Co. (the bu ness is now bein: ducted by Gulab Kal- ian). Public activities Was chairman and also treas. for a long period up to the time of his death of the Transvaal Dargi Mundal: mentber of the managing committee of the Bespoke 3 Employers’ Assoca.; committee member of the Transvaal Hindw Siva’Samai: also contributed his share to public work. Died at Johannesburg, April 15, 1937. KHAN. Kazi Beblol: dist, Surat andvi Gujarati and. “Arabic, Children: 6 sons and 4 daughters. Came to South Africa in Oct. 1894, landed at Dur ban.” “After a short stay. proceeded to Jo hannesburg. From Jo- hannesburg went to Zeerust in 1898 and then to Bulawayo, 5. Rhodesia. being one of the pioneer Indians and among. the first to. secure” the fra chise; he also inter- ested himself in acquiring a cémetery for Muslims. With headquarters in Bulawayo he carried on business in various parts, ma ps to Bechuanaland and the Kalahari. From 1901-6. established _ business, with six branch stores at Zeerust. in the firm name of B. B. Khan & Co, In 1906 transferred interests to Lichtenburg, where the firm, with four branch stores, is still actively engaged in commerce. being one of the leading Indian businesses in the district Thereisa wholesale buying house at cr. Kort & Commis: sionerSt., Johannesburg. Publicactivities: In 1911an active member of the Home Rule League. a strong sup- porter of Hindu-Musli co-operation. Took a prominent part in the public life of Mandvi; in 1919 founded the Mandvi Public Library; in 1922-25 being connected with Mahatma Gandhr’s movement, while loyal to the British connection was still patriotic in serving the interests of his countrymen: was v-presdt., Mandvi High School; patron, Mandvi Educational Society ; was presdt., Mandvi Khalifat Committee. In South Africa took part in the Passive Resistance struggle, 1908-14 ; had taken interest in all public efforts, contributing both service an money. Died in Johannesburg, March 12, 1937 I DIAN WHO'S WHO 349 KHAN, Rahim Karim; was Barrister- at-law, member of Lin- coln’s Inn; member Supreme Court of Judi- cature and; ad- vocate Supreme Court of South Africa (X.P.D.): b, Bomba: March 24, 1874: di Oct. 8, 1932. Daring Boer War acted as leader of Ambulance Corps at Colenso and Spion Kop, ete... giving services free, for which he was thanked by Government and decorated with the usual medal; was for many years joint secty. of the Natal Indian Congress. Repstd. Natal at S,ALC Conferences: was appointed by Government of Natal as member of Board of Examiners for Indian languages, On his death left practically his whole estate, ex ceeding £40,000, for Indian medical relief MEER, Cassim Hajee Suleman; & Surat City, Oct. 12, 1884. Died at Dundee, May'30, Educ. Surat city. Came to South Africa in 1896, Settled in Dundee, where he was in bus ness. He leading 1 district, prominently identifying himselt with public work Chairman of the Natal Indian Congress, Dui dee Branch; presdt of the Northern Natal Chamber of Commerce: presdt. of the Muslim Congrega Dundee and District Indian Football Assocn. ; was an official of practically all public bodies in Northern Natal; was a member of Congress deputation to the Minister of the Interior, Dr. D. I, Malan, in connection with the Class Areas Bill, 1925; repstd Natal at the S.A.1.C. Conferences from 1919. Was also a large donor of the Sastri College Building Fund. one of those responsible for starting the India Was a strong advocate of 3 In India repstd. Surat City at the All-India, Muslim. Educational Conference,” etected as one of the members of the reception committee Of 17; joint secty. of the reception committee of the All-india National Congress held at Surat City ; was a large donor towards, and instrumental toa great extent in, the erection of the Surat Islam Yatimkhana; first chairman of its committee. Collected a I money for the Khalifat Fund, which was signally recognised by its committee. consisting of distinguished Muslims. He is survived by his widow and the soas are Yousuf, Ebrahim, Mahomed and Suleman. presdt. of the","profession":"348, TH GOOLAM, Rasool ; (known alsd as Moon: shi): Commissioner for Oaths; 6"}]},{"page":4,"text":"THE SOUTH AFRICAN INDIAN WHO'S WHO 351 350 THE SOUTH AFRICAN INDIAN WHO’S WHO MOODLEY, Govind- amah ; b, Maritzby 1906; | d. of Charlie Nulliah, of Pieter. maritezburg ; mS. A Moodley. brassware manufacturer, of Dur. ban, September 10, two «, one d.: Vork Road Govt n School, Maritz: Passed Junior and Senior Indian Teacher Examination joined the st York Road Govern. NAGAR Gopal; . Kachholi, dist. Surat, 1880; educ. Kachholi Came to South Africa and joined his brother, Icharam Gopal, one of the first Indians to work as a tailor in Johannesburg. Busi. trolled by his brother, Kalian Gopal. and son, Vasanjee Nagar, Kan: chhodbhai and’ Gov- indbhai Nagar. Public activites = Former presdt., and also_ was MAKAN Jogi, mer- chant tailor; 6. Gan- devi, Baroda State 1883 ; v. sof late Jogi Hira! “two «, five d educ. Gandevi. Came to South Africa in 1901 settled in Johannes: burg, where was in business with his brothers, tradin; Jogi & Co. Took over the business concern in 1930. After death, firm is. pow being con: ducted “by his” son, Mamilatl Makan, standing cricket player, repstd. Transvaal Colourds on three occasions, 1907-9-23; repstd. Pretoria for many years, played from 1902 till \"34. Was also a fine swimmer, cyclist, boxer, and weight-lifter. W fone of the best knoven figures in South African sporting MEHTA, Jaya- shanker Bhaichand; fiew of Revas Shanker, Jagjivan Dr. P. J. Mehta, Ran- youn: 6 Morvi. Kethi- War, 1878: died, Dur- ban! Aug. 5. 1931, On ment Indian School, Prcty.transvaal Darel 4. Public activr leaving schoot was in resigning on her mar- Mundal; —v.-presdt., feo tember Ot the. Transvaal Dargi Mundat and the service of Dhuram: riage. Public activities : Took a keen interest in all Transvaal Hindu Seva Samaj; member of the Hindy one of the pioneers of the Das mumigrin the pat, one of the large matters affecting the Indian community, particularly Crematorium ‘Committee. A. generous iver to. all Transvaal, Died on board ship Apart Tse Soon women and ciren welfare Wasa member of the eerie public appeals. Died Kachholitndia, Nov. Svaal. Died on Foard ship, April 11, 1038, mpanied Maritzburg Indian Parliamentary Debating Society 10. 1937 occupying at one session a “ministerial” appointment, being “Minister of Education”; was pret. Indian . Women’s feague. Died July 23, 1 NAIDOO, P. K ndhi to South Mrica, arriving in Durban, Dec.. 1896 Was a clerk in Mr. Gandhi's ofhee till 1900 and for a short time was with the late Parsee Rustomjee. He started own business in Grey Strect. Durban, adjoining the present mosque. where he established Nery successful and soled concern. He gave freely of what he had, £100 to the Sastri Col’exe Building Fuad, and in_his will leit £1,250 for educational scholarships. £250 for a hospital at Durban, £130 for the erection of the Kathiwar Arya Mandal building and many other amounis to. private and public charities. \"For his donations during the Great’ War, he was thanked by the then Mayor of Durl survived by his widow and two sons Sh b, Natal. eventually Settled in the Trans. vaal. Took a promin- ent part in” public activities. and was the secty. of the Transvaal India: British Assocn: Visited India to secure co-operation of the Government and people for the removal of Indian disabilities in Somti Africa. Was in Maritzburg in the Indian strike of 1913, arrested and re- sel on £1,000 hail, Died in Jolannesburg. MAHARAJ, Boboolal; o. s. of late Hameaj Maharaj : &. Port Eliza beth, June 17, 1884 died’ isi Pretoria, 19% m. Rajawanthi 3rd d. of Ramphall, of Pre tora. Was’ in busi- ness; Indian interpreter of the magistrate ancl Supreme Courts: pro- perty owner. Public actinitics : Vspresilt TAC. (Pretoria ranch} und represented Trans: vaal at various sess of the SA.LC. Conter- ence, including the first MOQOSA, Hajee Is- mail Amod Hatfejee; keshwar, Bom! tay, Feb 6. 1890. 7 s.0f A. H. Moosa, mer- chant, Durban, “Man- aged firm of A. H. Noosa. Gill 1914, when took charge of the Bombay office; made himself’ very popular with commercial and public life of Bombay Was made member of the Willingdon Club, the Islam Club and He is ital and Conference. Treas. of , the Imperial Tadian the Transvaal Indian Defence Assocn.: v-presdt. Citizenship Assoc NAIR, Kamalam: Transvaal British Indian Assocn., which has now Bombay. Toured teacher: 5. Durban merged into the Congress, Took part in Passive Europe, 1921, on return brought back a Rolls Koyce, May 17, 1913: ¢. s Resistance struggle in 1909, suffering a term of three being first indian owner. Formed Red Crescent of Ramsamy Naidoo, months’ presdt., Hindu Seva MURUGAN, Tom, Society, of which he was elected treas.. helped in of Point Koad, Durban Femple: as one of the leading, Indians presented to Madras residency Salth\"atvigan vistors Gateresining SAL deputation ede: Depot Road Govt HRM. the Prince of Wales; chairman af the Hindu 1850. \\ pioneer feiat ind Beyer's Delegation. Was keen on starting large Indian School; St red toadmita certain nuntber of workers Chelmsford Road, Dur- ite o doned the oject. Was largely ban. Passed Indian not being pre} in the forward position; started. in the year’ 1902 ple scale, ‘The family i from India, aba repstd, Transvaal on three occasions; v.capt,, 1913 as large. farming. i responsible for the Indian ‘Traders’ menor n Junior Teachers’ Cer- and 1924: capt., 1926. played for years for. Pretor terest.\" Public activi tothe Fazhi Hussain. Delegation, Kee ate, 1928: Ta, inter-district, captained the Pretorians F.C. for many tes: Had_great Education, donated 10,000 rupees for scholarship DH. In 1928 joined years. V.-capt. of the first South African soccer team _ fluence with all sections to the Aligarh University and has provided. co the teaching staff of to India, 1921-22. Presdt. twice P.D.LE.A.; also of the community mercial scholarships for South African Indian students the -M._K. Gandhi life v.-presdt. and treas, for last IN years.’ Was was widely known and at Bombay. A donor to the Sastri College Building ntimel School and in prominently connected with the tour of the All-India respected amony all Fund. One of the founders of the Orient Club, 932 Roosfontein Gavt. a its football team to the Union, 1934, Also played rugby sections. of the ‘com. Durban. A'man with progressive views and an ardent Indian. School. Retired owing to illness in 1995. since 1905, repstd. Pretoria in eleven inter-district munity. Died at his worker for the uplift of the commu Public actives | Teeas., Women’s Auxibary of the matches, captained nine others, and on one occasion Fm at New Glaxgow. the Indo-European. Joint Council for, several ye Natal Indian Teachers” Society and was _clos:ty capt. of the Transvaal ; played for Standards ; captained pril, 1927. survived On his return, after having completed his pilgrimage, connected with all her husband's public activities the club for 16 years, was a life v.-presdt. An out- by two brothers, namely, T. Moonsamy, T. P. Sam, died at Jedda, Arabia. April 17, 1934. Died February 19, 1939.","records":[{"fullName":"THE SOUTH","rawText":"THE SOUTH AFRICAN INDIAN WHO'S WHO 351 350 THE SOUTH AFRICAN INDIAN WHO’S WHO MOODLEY, Govind- amah ; b, Maritzby 1906; | d. of Charlie Nulliah, of Pieter. maritezburg ; mS. A Moodley. brassware manufacturer, of Dur. ban, September 10, two «, one d.: Vork Road Govt n School, Maritz: Passed Junior and Senior Indian Teacher Examination joined the st York Road Govern. NAGAR Gopal; . Kachholi, dist. Surat, 1880; educ. Kachholi Came to South Africa and joined his brother, Icharam Gopal, one of the first Indians to work as a tailor in Johannesburg. Busi. trolled by his brother, Kalian Gopal. and son, Vasanjee Nagar, Kan: chhodbhai and’ Gov- indbhai Nagar. Public activites = Former presdt., and also_ was MAKAN Jogi, mer- chant tailor; 6. Gan- devi, Baroda State 1883 ; v. sof late Jogi Hira! “two «, five d educ. Gandevi. Came to South Africa in 1901 settled in Johannes: burg, where was in business with his brothers, tradin; Jogi & Co. Took over the business concern in 1930. After death, firm is. pow being con: ducted “by his” son, Mamilatl Makan, standing cricket player, repstd. Transvaal Colourds on three occasions, 1907-9-23; repstd. Pretoria for many years, played from 1902 till \"34. Was also a fine swimmer, cyclist, boxer, and weight-lifter. W fone of the best knoven figures in South African sporting MEHTA, Jaya- shanker Bhaichand; fiew of Revas Shanker, Jagjivan Dr. P. J. Mehta, Ran- youn: 6 Morvi. Kethi- War, 1878: died, Dur- ban! Aug. 5. 1931, On ment Indian School, Prcty.transvaal Darel 4. Public activr leaving schoot was in resigning on her mar- Mundal; —v.-presdt., feo tember Ot the. Transvaal Dargi Mundat and the service of Dhuram: riage. Public activities : Took a keen interest in all Transvaal Hindu Seva Samaj; member of the Hindy one of the pioneers of the Das mumigrin the pat, one of the large matters affecting the Indian community, particularly Crematorium ‘Committee. A. generous iver to. all Transvaal, Died on board ship Apart Tse Soon women and ciren welfare Wasa member of the eerie public appeals. Died Kachholitndia, Nov. Svaal. Died on Foard ship, April 11, 1038, mpanied Maritzburg Indian Parliamentary Debating Society 10. 1937 occupying at one session a “ministerial” appointment, being “Minister of Education”; was pret. Indian . Women’s feague. Died July 23, 1 NAIDOO, P. K ndhi to South Mrica, arriving in Durban, Dec.. 1896 Was a clerk in Mr. Gandhi's ofhee till 1900 and for a short time was with the late Parsee Rustomjee. He started own business in Grey Strect. Durban, adjoining the present mosque. where he established Nery successful and soled concern. He gave freely of what he had, £100 to the Sastri Col’exe Building Fuad, and in_his will leit £1,250 for educational scholarships. £250 for a hospital at Durban, £130 for the erection of the Kathiwar Arya Mandal building and many other amounis to. private and public charities. \"For his donations during the Great’ War, he was thanked by the then Mayor of Durl survived by his widow and two sons Sh b, Natal. eventually Settled in the Trans. vaal. Took a promin- ent part in” public activities. and was the secty. of the Transvaal India: British Assocn: Visited India to secure co-operation of the Government and people for the removal of Indian disabilities in Somti Africa. Was in Maritzburg in the Indian strike of 1913, arrested and re- sel on £1,000 hail, Died in Jolannesburg. MAHARAJ, Boboolal; o. s. of late Hameaj Maharaj : &. Port Eliza beth, June 17, 1884 died’ isi Pretoria, 19% m. Rajawanthi 3rd d. of Ramphall, of Pre tora. Was’ in busi- ness; Indian interpreter of the magistrate ancl Supreme Courts: pro- perty owner. Public actinitics : Vspresilt TAC. (Pretoria ranch} und represented Trans: vaal at various sess of the SA.LC. Conter- ence, including the first MOQOSA, Hajee Is- mail Amod Hatfejee; keshwar, Bom! tay, Feb 6. 1890. 7 s.0f A. H. Moosa, mer- chant, Durban, “Man- aged firm of A. H. Noosa. Gill 1914, when took charge of the Bombay office; made himself’ very popular with commercial and public life of Bombay Was made member of the Willingdon Club, the Islam Club and He is ital and Conference. Treas. of , the Imperial Tadian the Transvaal Indian Defence Assocn.: v-presdt. Citizenship Assoc NAIR, Kamalam: Transvaal British Indian Assocn., which has now Bombay. Toured teacher: 5. Durban merged into the Congress, Took part in Passive Europe, 1921, on return brought back a Rolls Koyce, May 17, 1913: ¢. s Resistance struggle in 1909, suffering a term of three being first indian owner. Formed Red Crescent of Ramsamy Naidoo, months’ presdt., Hindu Seva MURUGAN, Tom, Society, of which he was elected treas.. helped in of Point Koad, Durban Femple: as one of the leading, Indians presented to Madras residency Salth\"atvigan vistors Gateresining SAL deputation ede: Depot Road Govt HRM. the Prince of Wales; chairman af the Hindu 1850. \\ pioneer feiat ind Beyer's Delegation. Was keen on starting large Indian School; St red toadmita certain nuntber of workers Chelmsford Road, Dur- ite o doned the oject. Was largely ban. Passed Indian not being pre} in the forward position; started. in the year’ 1902 ple scale, ‘The family i from India, aba repstd, Transvaal on three occasions; v.capt,, 1913 as large. farming. i responsible for the Indian ‘Traders’ menor n Junior Teachers’ Cer- and 1924: capt., 1926. played for years for. Pretor terest.\" Public activi tothe Fazhi Hussain. Delegation, Kee ate, 1928: Ta, inter-district, captained the Pretorians F.C. for many tes: Had_great Education, donated 10,000 rupees for scholarship DH. In 1928 joined years. V.-capt. of the first South African soccer team _ fluence with all sections to the Aligarh University and has provided. co the teaching staff of to India, 1921-22. Presdt. twice P.D.LE.A.; also of the community mercial scholarships for South African Indian students the -M._K. Gandhi life v.-presdt. and treas, for last IN years.’ Was was widely known and at Bombay. A donor to the Sastri College Building ntimel School and in prominently connected with the tour of the All-India respected amony all Fund. One of the founders of the Orient Club, 932 Roosfontein Gavt. a its football team to the Union, 1934, Also played rugby sections. of the ‘com. Durban. A'man with progressive views and an ardent Indian. School. Retired owing to illness in 1995. since 1905, repstd. Pretoria in eleven inter-district munity. Died at his worker for the uplift of the commu Public actives | Teeas., Women’s Auxibary of the matches, captained nine others, and on one occasion Fm at New Glaxgow. the Indo-European. Joint Council for, several ye Natal Indian Teachers” Society and was _clos:ty capt. of the Transvaal ; played for Standards ; captained pril, 1927. survived On his return, after having completed his pilgrimage, connected with all her husband's public activities the club for 16 years, was a life v.-presdt. An out- by two brothers, namely, T. Moonsamy, T. P. Sam, died at Jedda, Arabia. April 17, 1934. Died February 19, 1939."}]},{"page":5,"text":"THE SOUTH AFRICAN OSMAN, Hajee PADAYACHEE, apen Marday ; being among the early conducted till the time Castle.” After a short large property owner. ‘An ardent worker for burg, where worked as break of the Boer War came back to Natal, Went on pilgrimage to Mecea in 1910. 0 Poon (Fakir Osman) and 6 de ughters removed to New Germany, where engaged in business 1913 came back to Maritz burg, opening tobacconist and general dealer's business, Was also property owner. in which he was Hindu Friendly Society, established in 1896, was one of the fi societies in the Transvaal. Was secty. of the Vania Kula Kshvatei Sabha, 1907. when a commencement of the Hindu Temple building 2 from 1915 to L938, 2 erected at his own expense additional buildings al s Died at Pietermaritzburg, Natal, 3 Seebaluk Panday Model School, Durban. joined firm of advo- with which he had been connected for the last hodji and Vatlabhbhai) Arrived in South came to Johannesburg. In 1912\" opened. busi- ness, wholesale produce merchants, in the name served in the Anglo Bocr War under Mr. Gandhi, awarded the Queen's Medal of the ‘Sydenham Indian Health Board and. Rate- appeared for this body before the Greater Durban Boundary “Commission, ple, Sea Cow Lake. at various sessions of the S.A.LC. Conferences held in many parts of the Allindia \"National Congress ‘at Lahore, in 1909-10. a keen sportsman, playing both football and coke; “was member Artie yerkenie ee played centre-half and later Was the’ organiser of the first football team to Johannesburg, 1899, and was once prominently associated with held many posts as an oficial of sport Was the donor of the Panday Bros.” Shield for Natal for Natal tennis championship, ‘Abe ‘Panday Shield for Natal Indian Boy Scouts started Patel & Sons, United Patidar Society: v.-presdt., Transvaal British Indian Assocn. ; Hindu Crematorium Committee : Seva Samaj ; presdt. Transvaal Indian Cong in the Civil Disobedience movement, 1921, chairman, Vaghecha Samasan Committee. movements concerning his with which he was not either Had been a generous Haripura Shreya Sadik Mundal Crimson League F.C. In India took part or indirectly connected. to the Patidar Hall and Library Scheme, Hindu Seva Samaj Gandhi Hall and Temple Fund. Johannesburg, September cricket, and a_Cup THE SOUTH AFRICAN INDIAN WHO'S WHO 353 PATEL, Muljibhai Girdharbhai (known as Mulji G. Patel) 3 Dharma), dist. Petiad (Baroda) ‘August 18, 1873 educ. Baroda High’ School. niatricu= lated 1898 (Bombay University). Came to South Africa 1902, Starting works book Keeper with — various firms : also interpreter, translator, general and estate agent. At one time or another was connected with. man Glasses of business. Was proprictor of Hombay Warehouse (silk): a director $. African Co-op Prudential Estates, bed. Waschieland soleagent for indian business of National Mutual Life Assocn. of Australasia, Ltd Jorburg. Ever since arrivalin S. Africa had taken part in public alfairs. One of the early associates of Mr. Gandhi his legal. office in Johannesburg I Beitish Indian. Assoen. Gomnt- secty. with Mr H. S. L. Pollak}. One of the petitioners to Parliament for removal of restrictions of Gold Law in 1919 which resulted in Act 37 of 1919. Was member deputation to Viceroy (Lord Reading) in 1922 in con- nection with South Atrican. «disabilities. During passage of Class Areas Hill took part in opposition to his measure and greatly. helped ‘Paddison cleputation tS investigation of South African affairs. Was a Transvaal representative to S.A.1.C. Conferences. for many years. Was one of founders (chairman 3 years) of the Hindw Crentatorium in Johannesburg—one of best known instititions of its kind in South Africa Greatly interested in all public movements for al Vancement of the community. Died in India, 1930 LLAY, Kumarsamy Krishnasamy; ¢ ‘Tanjore, Madras. ‘Dec. 25, 1867. Came to South Africa in 1884 jsited Transvaal and the Cape for the pi pose oF starting busi ness but eventually ‘opened a general dealer's store in Dur- ban, 190L; soon after ‘transferred interests to Greenwood Park. where had conducted ‘a successful business. Public work > Repstd. Natal at $.A.1.C. Con- ferences at Cape Town, Kimberley, Johannesburg and other places; took ive Resistance movement, under founder ‘of the Greenwood Park Indian School, 23. years ago, and the Ranganathan Temple; was trustee of the Umgeni S. S. Temple: was treas.,C.B-and S.1. Asscen Died at Greenwood Park, 193 PAUL, Henry Louis; 4h. Madras Presidency, March 1S. 1864; died! June 1, 1985: 1. Ellen Elizabeth Johnson, at Durban, Feb. 25. 1889: Sch. Arrived at Dur- ban in the barque Chwcoti, Sept. 3, 1881 Entered the Natal Railway Service in the same month ancl sub: sequently became asst maintenance store keeper. He left department five years later and was in service with the African Hoat- ing Company, Pont Durban, and later with the Durban Borough Police. On Jan. 3, 1889. entered the Civil Serviee, then at the Stanger Magistrate's Court, as Indian interpreter On Dec. 2 of the same year transferred on promotion as clerk and senior Indian interpreter, to the Chief Magistrate's Department. Durban, a position which he held under theee Governments—Natal Crown Colony Government, Responsible Government. and lastly. the Union Government, His splendid record was said to be unique in the service, autded to which was his exemplary, unblemished and excellent character, He retired! on March 18, 1924. He was thanked by the then Minister of Justice (Mr. de Wet) for the unique rccord of over 34 years’ continuous Government secvice, without a single day's absence.” Addresses, eulogising his services were presented to him by the staff of magistrates and other evil servants. with which the sar also associated itself. and also. the Indian community, He was also a keen public worker. particularly in the field of education, and was instrumental in establishing the first Govern:ent School toc Indians im Durban. He was a devout 2 Cath an_active worker for the Indian section of the Church. Through his efforts, the first priest to work exclusively among Indians and to take Charge of St. Anthony's Mission came out. Other positions he held included: Pirst presdt, and founder. Indian United Eleven Cricket Club: Natal Indian Football Assocn.; Greyvitle Sporting Assocn: Grevvitle Cycling “Chub; United “Sporting Assocn.> Higher Grade School Club; Natal Indian Educational Asscen : Higher Grade School Old Boys’ Assocn. Incian Benevolent Society: Indian Clerks and Inter: preters’ Assocn SAMMY, Mapplysamy Pillay; . Tanjore, about 1836, died Kimberley, August, 1933. 4 sons and 2 daughters. Leit Madras with his. parents for Mauritius. Tater he alone came to South Africa, among the pioneer Indians to settle in Port Elizabeth “Subsequently removed. to. Kimberley, where he was in business, being one of the prominent Indian citizens of the Diamond City, He was one of the first Indians to become a wholesale merchant in the Cape. He was highly respected by all sections of the community and was intimately krown to the many pioneer Europeans prominently connected with the developnient of Kimberley.","records":[{"fullName":"THE SOUTH","rawText":"THE SOUTH AFRICAN OSMAN, Hajee PADAYACHEE, apen Marday ; being among the early conducted till the time Castle.” After a short large property owner. ‘An ardent worker for burg, where worked as break of the Boer War came back to Natal, Went on pilgrimage to Mecea in 1910. 0 Poon (Fakir Osman) and 6 de ughters removed to New Germany, where engaged in business 1913 came back to Maritz burg, opening tobacconist and general dealer's business, Was also property owner. in which he was Hindu Friendly Society, established in 1896, was one of the fi societies in the Transvaal. Was secty. of the Vania Kula Kshvatei Sabha, 1907. when a commencement of the Hindu Temple building 2 from 1915 to L938, 2 erected at his own expense additional buildings al s Died at Pietermaritzburg, Natal, 3 Seebaluk Panday Model School, Durban. joined firm of advo- with which he had been connected for the last hodji and Vatlabhbhai) Arrived in South came to Johannesburg. In 1912\" opened. busi- ness, wholesale produce merchants, in the name served in the Anglo Bocr War under Mr. Gandhi, awarded the Queen's Medal of the ‘Sydenham Indian Health Board and. Rate- appeared for this body before the Greater Durban Boundary “Commission, ple, Sea Cow Lake. at various sessions of the S.A.LC. Conferences held in many parts of the Allindia \"National Congress ‘at Lahore, in 1909-10. a keen sportsman, playing both football and coke; “was member Artie yerkenie ee played centre-half and later Was the’ organiser of the first football team to Johannesburg, 1899, and was once prominently associated with held many posts as an oficial of sport Was the donor of the Panday Bros.” Shield for Natal for Natal tennis championship, ‘Abe ‘Panday Shield for Natal Indian Boy Scouts started Patel & Sons, United Patidar Society: v.-presdt., Transvaal British Indian Assocn. ; Hindu Crematorium Committee : Seva Samaj ; presdt. Transvaal Indian Cong in the Civil Disobedience movement, 1921, chairman, Vaghecha Samasan Committee. movements concerning his with which he was not either Had been a generous Haripura Shreya Sadik Mundal Crimson League F.C. In India took part or indirectly connected. to the Patidar Hall and Library Scheme, Hindu Seva Samaj Gandhi Hall and Temple Fund. Johannesburg, September cricket, and a_Cup THE SOUTH AFRICAN INDIAN WHO'S WHO 353 PATEL, Muljibhai Girdharbhai (known as Mulji G. Patel) 3 Dharma), dist. Petiad (Baroda) ‘August 18, 1873 educ. Baroda High’ School. niatricu= lated 1898 (Bombay University). Came to South Africa 1902, Starting works book Keeper with — various firms : also interpreter, translator, general and estate agent. At one time or another was connected with. man Glasses of business. Was proprictor of Hombay Warehouse (silk): a director $. African Co-op Prudential Estates, bed. Waschieland soleagent for indian business of National Mutual Life Assocn. of Australasia, Ltd Jorburg. Ever since arrivalin S. Africa had taken part in public alfairs. One of the early associates of Mr. Gandhi his legal. office in Johannesburg I Beitish Indian. Assoen. Gomnt- secty. with Mr H. S. L. Pollak}. One of the petitioners to Parliament for removal of restrictions of Gold Law in 1919 which resulted in Act 37 of 1919. Was member deputation to Viceroy (Lord Reading) in 1922 in con- nection with South Atrican. «disabilities. During passage of Class Areas Hill took part in opposition to his measure and greatly. helped ‘Paddison cleputation tS investigation of South African affairs. Was a Transvaal representative to S.A.1.C. Conferences. for many years. Was one of founders (chairman 3 years) of the Hindw Crentatorium in Johannesburg—one of best known instititions of its kind in South Africa Greatly interested in all public movements for al Vancement of the community. Died in India, 1930 LLAY, Kumarsamy Krishnasamy; ¢ ‘Tanjore, Madras. ‘Dec. 25, 1867. Came to South Africa in 1884 jsited Transvaal and the Cape for the pi pose oF starting busi ness but eventually ‘opened a general dealer's store in Dur- ban, 190L; soon after ‘transferred interests to Greenwood Park. where had conducted ‘a successful business. Public work > Repstd. Natal at $.A.1.C. Con- ferences at Cape Town, Kimberley, Johannesburg and other places; took ive Resistance movement, under founder ‘of the Greenwood Park Indian School, 23. years ago, and the Ranganathan Temple; was trustee of the Umgeni S. S. Temple: was treas.,C.B-and S.1. Asscen Died at Greenwood Park, 193 PAUL, Henry Louis; 4h. Madras Presidency, March 1S. 1864; died! June 1, 1985: 1. Ellen Elizabeth Johnson, at Durban, Feb. 25. 1889: Sch. Arrived at Dur- ban in the barque Chwcoti, Sept. 3, 1881 Entered the Natal Railway Service in the same month ancl sub: sequently became asst maintenance store keeper. He left department five years later and was in service with the African Hoat- ing Company, Pont Durban, and later with the Durban Borough Police. On Jan. 3, 1889. entered the Civil Serviee, then at the Stanger Magistrate's Court, as Indian interpreter On Dec. 2 of the same year transferred on promotion as clerk and senior Indian interpreter, to the Chief Magistrate's Department. Durban, a position which he held under theee Governments—Natal Crown Colony Government, Responsible Government. and lastly. the Union Government, His splendid record was said to be unique in the service, autded to which was his exemplary, unblemished and excellent character, He retired! on March 18, 1924. He was thanked by the then Minister of Justice (Mr. de Wet) for the unique rccord of over 34 years’ continuous Government secvice, without a single day's absence.” Addresses, eulogising his services were presented to him by the staff of magistrates and other evil servants. with which the sar also associated itself. and also. the Indian community, He was also a keen public worker. particularly in the field of education, and was instrumental in establishing the first Govern:ent School toc Indians im Durban. He was a devout 2 Cath an_active worker for the Indian section of the Church. Through his efforts, the first priest to work exclusively among Indians and to take Charge of St. Anthony's Mission came out. Other positions he held included: Pirst presdt, and founder. Indian United Eleven Cricket Club: Natal Indian Football Assocn.; Greyvitle Sporting Assocn: Grevvitle Cycling “Chub; United “Sporting Assocn.> Higher Grade School Club; Natal Indian Educational Asscen : Higher Grade School Old Boys’ Assocn. Incian Benevolent Society: Indian Clerks and Inter: preters’ Assocn SAMMY, Mapplysamy Pillay; . Tanjore, about 1836, died Kimberley, August, 1933. 4 sons and 2 daughters. Leit Madras with his. parents for Mauritius. Tater he alone came to South Africa, among the pioneer Indians to settle in Port Elizabeth “Subsequently removed. to. Kimberley, where he was in business, being one of the prominent Indian citizens of the Diamond City, He was one of the first Indians to become a wholesale merchant in the Cape. He was highly respected by all sections of the community and was intimately krown to the many pioneer Europeans prominently connected with the developnient of Kimberley."}]},{"page":6,"text":"354 THE SOUTH THE SOUTH AFRICAN INDIAN WHO'S WHO 355 SINGH, Buldav Mahadev ' ¢. s, of late Buldav Singh I RAWAT, Ebrahim Cassim ; 6. Nana Varachha. dist. Surat, about 1850, died, 1929. \\ pioneer merchant in Natal, Settled in Mar- iteburg, where he spent the rest of his. life Founded the firm of E. C. Rawat in 1880, I dealers. Was ly respected by ‘sections of the com unity. Is. survived by two sons. Moosa Ebrahim Rawat, Dur- ban, and il Eb- fabigy Rawat, Maritz- burg,and Mrs. Mahomed Jeewa, of Durban, and numerous grandchildren. PILLAY, Muthu- samy Nadesa Porayar, dist. 1 Madras, 1867: educ Porayar. Came to South Africa in 1896, settled in Durban. A. few years afterwards SADER, Hoosen Fb- rahi 6. Kharod, India, 1878; came to South Africa in 1894 t stayed in Durban, then came to Lady- smith, 1897. Was in rivate employment. ness in the fiem name of Ameer & Hoosen. In 1909 paid a short visit to India. After feturning increased business to a fairly educ, Victoria Government. Indian School, Boys’ Model School, Smith Street, and Higher Grade Gov ernmient Indian School,‘ Alice Street, Durban m. daughter of late Dulsingar Singh of Kearsney. First in private employment, opened his first busi ness in partnership large Native _ trade with his father at Cato Also had few branches Manor. Has since been j in the district of Klip 1 engaged in various trades—wood and coal merchant Al by alt cho knew: him: property, butchery, quarry. etc.—being among the During the Boer W returned to. Durba where he took up per manent residence Started business as cigar manufacturer was a partner im the Imperial Cigar Manu: facturing Co. Resigned and started on his own. eventually joining the Standard Cigar Co, Durban. River. He was highly respect be his second Public activities © Was chairman, then trustee, of He was very keen on education, has sent h few colonial-born Indians to show outstanding qualities the S.V Temple, Umgeni Road, ‘Durban: a keen son, Ahmed, first from Ladysmith to Sastri College. of business enterprise. Piblicactveitiess Was tc presdt, Supporter of vernacular education and of Hind Durban, who had passed the London Matriculation NC) trustee! Durban Hindu. Temples wast eene ol RAWAT, Hajee mail Ebrahim ; 6. Nanavarachha, ‘dist Surat, 1877. Came to South Africa, follows social reforms. \"Survived “ty tee aang ee Examination, im_June, 84: since proceeded to N.C: trustee Durban Hindu Temple” waa one of lanikam Pillay “and Phangan ‘ly ed: Birmingham Cniversty, England. to study medicine, (OSE fesponsile for he building of he Aryan Auguse’S1, 1938 Avtor hs death the mame ot the fim wascchanged to t Home and Schoo! at Cato Manor ; preslt. eee es, Ebon wed by widow. six'sons SPorts Ground Assocn, and official of ‘! eldest son, Ebrahim, Ls sur bodies. Formerly a leading racehorse owner. Died. ing his father 10 yea SOBRUN. Dha and five daughters. His death was mourned by a es se Jater. “Joined” his dharie ; was Civil Ser. very large family settled in South Africa and in India father’s business in vant Senior Interpreter Died 17th July, 1936. Maritzbury, which 1s now bein’ conducted by his sons. Mahome Ismail Rawat, Suliman 1. Rawat. Goolam Hoo- aml Commissimer for Oaths: J. May 14, 1880. at Duff's Road Natal educ. at the Rahway Day and Nigtt Schools. SINGH, Chundoo ; 5. of Ba &. Jaip to Natal in 1883, After sen I. Rawat, Abdool In 1908 serving the period of ; 01903 m. youngest Hck 1 \"Raat and 42, 1008. youngest his. contract. started ‘ima Ismail Rawat, Mewvand Mes. Dab farming, ater, opened jade a pilgrimage af Pictermaritzbon neral dealer's store. Mecca in 133. 2, She etermaritzburg SHADAZADEE, Was a large property Mrs. Abdulla; Moradabad, India, 877: 2nd d. of late Fedahosseni ; _m. late Abdulla’ Minda, for merly merchant, Durban. four s.. four @.: Came to Natal by SS “Foyle.” in 1888 1. Public actwittes Took prominent part in the Indian strike Of1913. A founder of the Gopallal Hindu Temple, Verulam ; founder and president of the Shree Ramayan Sabha, Oakford. Was nl progressive old colonist of the day. Was first employed. on the fate Natal Government Railways, as messenger, timekeeper of India and Native staff, and latterly as clerk-in-charge of the Railway Post Ortice, Durban. | Keceived appointment ia the Union Civ i highly esteemed by ail sections of the comm Died June 15, 1030, at Mlaritsbutg RUSTOMJEE, Parsee, merchant and philanthropist: 6 India. One. of the rvieg as oe sppoinkmen c settled in Durban ‘one of the leading Hin South Africa and con: transterreil, on promotion, to the Law Courts, Durbaa ployment started own 1938, 2d. Died, September 6, 1938. Borough Market, which was then located in the oid Empire Theatre building, now Central public life since his arrival. Suffered se terms of in prisonment during the Senior Indian interpretership. and on January. 13, 1935, was appointed Commissioner for Oaths, being the first Indian Civil Servant in Natal to have the appointment conferred upon him. He hal taken a TIKLY, Hajee Ismail Kholvsd, One of the jioneer \"merchants of ‘I Durban in 1885, Passive Resistance rominent part in Hindu religious. educational, soe Post.Offce. She was ten 188 Passive | Resistance prominent part i Hind Fligious, educations, sci {aR HE Bae iain women to cuter eommersat Abooaitr Aad, Durban. fa cae Tans death bequeathed, with ‘ . Me business. She subsequently transferred business and started business in Preto ustees of the following institutions: (1) Shri in [M18 commenced firm of War returned to India, from there got his wile, Jerbai, the Thakurdwara and Dharmasala, Durban ithe leadiny interests to Overport : c1 lay he came back to major portion of his Hindi Hindu Temple ine Sata). es Sie ane Finding Se Sahidon & Sone V4\" Rechan'ank Vosin im 1908 agent ok Ub Seton’ ta Preveeature “He estate for the use of Sabha, Overport, Durban (the first Society to bring out Trading as’ Sahidon & Sons 1\\, Roshan’ and Yassin in 1902 again took up residence in Pretersb Wloactt the Indian community. a Hindi teacher and preacher from India); (3) NagriPar- Mahomed). general dealers, butchers and refreshment Und took an active interest inthe Mosque’ work at erecting the MK. charani Sabha, Howick, Natal; (4) School manager room. Was large property owner. Public actieities ‘Kholvad, Survived by three sons | -Amod (Pretersbure) Gandhi Library, Rustomjee Hall, orphanayes. schools Of the Overpore S.R'S. Goverame Indian Charitably minded, being a large donor to, Islamia Suleman’ (Zeerust) and Mahomed.” (Pietersburg. wens me eetGational ‘requirements. Hix ‘beavest School—appointed \"by the Education eeeasneaan Madressa, Overport, Died at her residence, Ovesie-rt Died at Zeerust 1919. is the highest gift to the Indian community in SA of Natal Province. Died August 13, 1934. July 7, 1939. :","records":[{"fullName":"354 THE","rawText":"354 THE SOUTH THE SOUTH AFRICAN INDIAN WHO'S WHO 355 SINGH, Buldav Mahadev ' ¢. s, of late Buldav Singh I RAWAT, Ebrahim Cassim ; 6. Nana Varachha. dist. Surat, about 1850, died, 1929. \\ pioneer merchant in Natal, Settled in Mar- iteburg, where he spent the rest of his. life Founded the firm of E. C. Rawat in 1880, I dealers. Was ly respected by ‘sections of the com unity. Is. survived by two sons. Moosa Ebrahim Rawat, Dur- ban, and il Eb- fabigy Rawat, Maritz- burg,and Mrs. Mahomed Jeewa, of Durban, and numerous grandchildren. PILLAY, Muthu- samy Nadesa Porayar, dist. 1 Madras, 1867: educ Porayar. Came to South Africa in 1896, settled in Durban. A. few years afterwards SADER, Hoosen Fb- rahi 6. Kharod, India, 1878; came to South Africa in 1894 t stayed in Durban, then came to Lady- smith, 1897. Was in rivate employment. ness in the fiem name of Ameer & Hoosen. In 1909 paid a short visit to India. After feturning increased business to a fairly educ, Victoria Government. Indian School, Boys’ Model School, Smith Street, and Higher Grade Gov ernmient Indian School,‘ Alice Street, Durban m. daughter of late Dulsingar Singh of Kearsney. First in private employment, opened his first busi ness in partnership large Native _ trade with his father at Cato Also had few branches Manor. Has since been j in the district of Klip 1 engaged in various trades—wood and coal merchant Al by alt cho knew: him: property, butchery, quarry. etc.—being among the During the Boer W returned to. Durba where he took up per manent residence Started business as cigar manufacturer was a partner im the Imperial Cigar Manu: facturing Co. Resigned and started on his own. eventually joining the Standard Cigar Co, Durban. River. He was highly respect be his second Public activities © Was chairman, then trustee, of He was very keen on education, has sent h few colonial-born Indians to show outstanding qualities the S.V Temple, Umgeni Road, ‘Durban: a keen son, Ahmed, first from Ladysmith to Sastri College. of business enterprise. Piblicactveitiess Was tc presdt, Supporter of vernacular education and of Hind Durban, who had passed the London Matriculation NC) trustee! Durban Hindu. Temples wast eene ol RAWAT, Hajee mail Ebrahim ; 6. Nanavarachha, ‘dist Surat, 1877. Came to South Africa, follows social reforms. \"Survived “ty tee aang ee Examination, im_June, 84: since proceeded to N.C: trustee Durban Hindu Temple” waa one of lanikam Pillay “and Phangan ‘ly ed: Birmingham Cniversty, England. to study medicine, (OSE fesponsile for he building of he Aryan Auguse’S1, 1938 Avtor hs death the mame ot the fim wascchanged to t Home and Schoo! at Cato Manor ; preslt. eee es, Ebon wed by widow. six'sons SPorts Ground Assocn, and official of ‘! eldest son, Ebrahim, Ls sur bodies. Formerly a leading racehorse owner. Died. ing his father 10 yea SOBRUN. Dha and five daughters. His death was mourned by a es se Jater. “Joined” his dharie ; was Civil Ser. very large family settled in South Africa and in India father’s business in vant Senior Interpreter Died 17th July, 1936. Maritzbury, which 1s now bein’ conducted by his sons. Mahome Ismail Rawat, Suliman 1. Rawat. Goolam Hoo- aml Commissimer for Oaths: J. May 14, 1880. at Duff's Road Natal educ. at the Rahway Day and Nigtt Schools. SINGH, Chundoo ; 5. of Ba &. Jaip to Natal in 1883, After sen I. Rawat, Abdool In 1908 serving the period of ; 01903 m. youngest Hck 1 \"Raat and 42, 1008. youngest his. contract. started ‘ima Ismail Rawat, Mewvand Mes. Dab farming, ater, opened jade a pilgrimage af Pictermaritzbon neral dealer's store. Mecca in 133. 2, She etermaritzburg SHADAZADEE, Was a large property Mrs. Abdulla; Moradabad, India, 877: 2nd d. of late Fedahosseni ; _m. late Abdulla’ Minda, for merly merchant, Durban. four s.. four @.: Came to Natal by SS “Foyle.” in 1888 1. Public actwittes Took prominent part in the Indian strike Of1913. A founder of the Gopallal Hindu Temple, Verulam ; founder and president of the Shree Ramayan Sabha, Oakford. Was nl progressive old colonist of the day. Was first employed. on the fate Natal Government Railways, as messenger, timekeeper of India and Native staff, and latterly as clerk-in-charge of the Railway Post Ortice, Durban. | Keceived appointment ia the Union Civ i highly esteemed by ail sections of the comm Died June 15, 1030, at Mlaritsbutg RUSTOMJEE, Parsee, merchant and philanthropist: 6 India. One. of the rvieg as oe sppoinkmen c settled in Durban ‘one of the leading Hin South Africa and con: transterreil, on promotion, to the Law Courts, Durbaa ployment started own 1938, 2d. Died, September 6, 1938. Borough Market, which was then located in the oid Empire Theatre building, now Central public life since his arrival. Suffered se terms of in prisonment during the Senior Indian interpretership. and on January. 13, 1935, was appointed Commissioner for Oaths, being the first Indian Civil Servant in Natal to have the appointment conferred upon him. He hal taken a TIKLY, Hajee Ismail Kholvsd, One of the jioneer \"merchants of ‘I Durban in 1885, Passive Resistance rominent part in Hindu religious. educational, soe Post.Offce. She was ten 188 Passive | Resistance prominent part i Hind Fligious, educations, sci {aR HE Bae iain women to cuter eommersat Abooaitr Aad, Durban. fa cae Tans death bequeathed, with ‘ . Me business. She subsequently transferred business and started business in Preto ustees of the following institutions: (1) Shri in [M18 commenced firm of War returned to India, from there got his wile, Jerbai, the Thakurdwara and Dharmasala, Durban ithe leadiny interests to Overport : c1 lay he came back to major portion of his Hindi Hindu Temple ine Sata). es Sie ane Finding Se Sahidon & Sone V4\" Rechan'ank Vosin im 1908 agent ok Ub Seton’ ta Preveeature “He estate for the use of Sabha, Overport, Durban (the first Society to bring out Trading as’ Sahidon & Sons 1\\, Roshan’ and Yassin in 1902 again took up residence in Pretersb Wloactt the Indian community. a Hindi teacher and preacher from India); (3) NagriPar- Mahomed). general dealers, butchers and refreshment Und took an active interest inthe Mosque’ work at erecting the MK. charani Sabha, Howick, Natal; (4) School manager room. Was large property owner. Public actieities ‘Kholvad, Survived by three sons | -Amod (Pretersbure) Gandhi Library, Rustomjee Hall, orphanayes. schools Of the Overpore S.R'S. Goverame Indian Charitably minded, being a large donor to, Islamia Suleman’ (Zeerust) and Mahomed.” (Pietersburg. wens me eetGational ‘requirements. Hix ‘beavest School—appointed \"by the Education eeeasneaan Madressa, Overport, Died at her residence, Ovesie-rt Died at Zeerust 1919. is the highest gift to the Indian community in SA of Natal Province. Died August 13, 1934. July 7, 1939. :","profession":"354 THE SOUTH THE SOUTH AFRICAN INDIAN WHO'S WHO 355 SINGH, Buldav Mahadev ' ¢"}]},{"page":7,"text":"356 THE SOUTH AFRICAN SODHA, Ratanjhi Mulji; 6° Rajkot, dist Kathiawar, 1885! died Aug. 12. 1930; duc Rajkot “High ‘School ter schooling became business manager of The Kathiawar Times At this time became connected with Mahatma (then Mr.) Gandhi, being the Printer Of the famous green pamphlet. con- taining. grievances of Natal Indians, He de cided, on being invited by, Mr.’Gandhi.. to coine out to Natal in order*to serve his countrymen. On arrival in INDIAN WHO'S WHO Natal joined late Mr. Madanjit in founding the International Printing Works, which later printed The Indian Opinion. After few years resigned and started business. At outbreak of Passive Resistance in 1907 left business and joined Mr. Gandhi in the Transvaal and served with his wife, both being con vieted, suffering several terms of imprisonment In 1911 took up residence in Transvaal. being a mitted as an educated entrant with six other Indians Always associated himself with public. work right up to time of his death. Founded Gujarati Samachre His friendship with the Indian Nationalist. leader, Mahatma Gandhi, continued throughout, to whom he gave his sons, Revanshanker, who suifeced. imprison: ment in the 1913 struggle, ancl Chotalal who was ae Phoenix and at Sabarmati’ with him. Attended the S.A.LC. Conference us Transvaal delegate to. the Durban sexsions which were presided over by Mrs Sarojini Naidu RHODESIAN SECTION ABDULA Harun; wholesale merchant : 6 Cutch “Koday, Cutch, 1885; ¢. 5.’ of late Harun Hajee Omar; four s., Jushab Abdula, Abdul Saccoor Abdula Ebrahim Abdula Harun Abdula; three .; educ. Bombay City In’ 1901 came to the Transvaal, in 1906 to. Lourenco Marques, where joined the staff as bookkeeper of Jacaria Hajee Amod & Co. In 1915 con ducted the branch store of Jacaria Hajee Amod & Co., trading as Casa Abdula Harun. In 1926 went back to India and left business in charze of his sons, Joosub Abdula and Abdul Saccoor Abdula In 1933 business was transferred to the name of the three elder brothers who trade as Jushab Abdula & Co. and also Casa Abdula Harun, agents for Goodveat foot products and Phillips soles. Public achvifies Took (part in all public Muslim movements. Died at Cutch Koday, 1934 DESAI, Gulabbhai Makenji ; merchant &. Kattargam, dist Surat. 1892. 5th s. of late Makenji Naranji Desai; twos., one d. educ. Mission High School. Surat. On leaving school came to Southern Rhodesia in 1909, stayed at Selu- kwe ‘joining the firm of Bhimji R. Naik In 1915 started own business as_ general merchant in Gwelo and Selukwe. In’ 1938 re. joined the firm of Bhunji R Naik managing head office at Salisbury. Public act cities Was Chairman of the Gwelo Hindu Society; rep. Gwelo at the Hindu Conference at Salisbury, 1936 Member of the Coloured School Co Keen on education, has his daughter at the Kanya Maha Vidalya, of Raroda. Recridfiows. Reading and Indian politics. Died at Salisbury, 1938, Frected for the medical needs of the Indi community by the Indian-A(rican Line. (formerly Andrew Weir & Co.) now the Bank Line. Ltd. The building, which cost over £5,000, is an annexe of the King Edward VIII Hospital at Durban, and is meeting a very useful purpose as an out-patient depart nt. THE SOUTH AFRICAN INDIA WHO'S WHO 357 HIGHWOOD DAIRIES (Established 1914) RAW Recommended by the Medical Profession for INVALIDS AND BABIES Cows in Pi famous Fedig: ldock with the ‘arna- tion” Bull in the forefront Section of the Byre the Highwood Dairies. Section of Dairy 243 D’Aintree Avenue, SYDENHAM, DURBAN. Phone 8-8991","records":[{"fullName":"356 THE","rawText":"356 THE SOUTH AFRICAN SODHA, Ratanjhi Mulji; 6° Rajkot, dist Kathiawar, 1885! died Aug. 12. 1930; duc Rajkot “High ‘School ter schooling became business manager of The Kathiawar Times At this time became connected with Mahatma (then Mr.) Gandhi, being the Printer Of the famous green pamphlet. con- taining. grievances of Natal Indians, He de cided, on being invited by, Mr.’Gandhi.. to coine out to Natal in order*to serve his countrymen. On arrival in INDIAN WHO'S WHO Natal joined late Mr. Madanjit in founding the International Printing Works, which later printed The Indian Opinion. After few years resigned and started business. At outbreak of Passive Resistance in 1907 left business and joined Mr. Gandhi in the Transvaal and served with his wife, both being con vieted, suffering several terms of imprisonment In 1911 took up residence in Transvaal. being a mitted as an educated entrant with six other Indians Always associated himself with public. work right up to time of his death. Founded Gujarati Samachre His friendship with the Indian Nationalist. leader, Mahatma Gandhi, continued throughout, to whom he gave his sons, Revanshanker, who suifeced. imprison: ment in the 1913 struggle, ancl Chotalal who was ae Phoenix and at Sabarmati’ with him. Attended the S.A.LC. Conference us Transvaal delegate to. the Durban sexsions which were presided over by Mrs Sarojini Naidu RHODESIAN SECTION ABDULA Harun; wholesale merchant : 6 Cutch “Koday, Cutch, 1885; ¢. 5.’ of late Harun Hajee Omar; four s., Jushab Abdula, Abdul Saccoor Abdula Ebrahim Abdula Harun Abdula; three .; educ. Bombay City In’ 1901 came to the Transvaal, in 1906 to. Lourenco Marques, where joined the staff as bookkeeper of Jacaria Hajee Amod & Co. In 1915 con ducted the branch store of Jacaria Hajee Amod & Co., trading as Casa Abdula Harun. In 1926 went back to India and left business in charze of his sons, Joosub Abdula and Abdul Saccoor Abdula In 1933 business was transferred to the name of the three elder brothers who trade as Jushab Abdula & Co. and also Casa Abdula Harun, agents for Goodveat foot products and Phillips soles. Public achvifies Took (part in all public Muslim movements. Died at Cutch Koday, 1934 DESAI, Gulabbhai Makenji ; merchant &. Kattargam, dist Surat. 1892. 5th s. of late Makenji Naranji Desai; twos., one d. educ. Mission High School. Surat. On leaving school came to Southern Rhodesia in 1909, stayed at Selu- kwe ‘joining the firm of Bhimji R. Naik In 1915 started own business as_ general merchant in Gwelo and Selukwe. In’ 1938 re. joined the firm of Bhunji R Naik managing head office at Salisbury. Public act cities Was Chairman of the Gwelo Hindu Society; rep. Gwelo at the Hindu Conference at Salisbury, 1936 Member of the Coloured School Co Keen on education, has his daughter at the Kanya Maha Vidalya, of Raroda. Recridfiows. Reading and Indian politics. Died at Salisbury, 1938, Frected for the medical needs of the Indi community by the Indian-A(rican Line. (formerly Andrew Weir & Co.) now the Bank Line. Ltd. The building, which cost over £5,000, is an annexe of the King Edward VIII Hospital at Durban, and is meeting a very useful purpose as an out-patient depart nt. THE SOUTH AFRICAN INDIA WHO'S WHO 357 HIGHWOOD DAIRIES (Established 1914) RAW Recommended by the Medical Profession for INVALIDS AND BABIES Cows in Pi famous Fedig: ldock with the ‘arna- tion” Bull in the forefront Section of the Byre the Highwood Dairies. Section of Dairy 243 D’Aintree Avenue, SYDENHAM, DURBAN. Phone 8-8991","profession":"356 THE SOUTH AFRICAN SODHA, Ratanjhi Mulji; 6° Rajkot, dist Kathiawar, 1885! died Aug"}]}]}